constraint/__init__.py
constraint/compat.py
constraint/version.py
examples/__init__.py
examples/abc/__init__.py
examples/abc/abc.py
examples/coins/__init__.py
examples/coins/coins.py
examples/crosswords/__init__.py
examples/crosswords/crosswords.py
examples/einstein/__init__.py
examples/einstein/einstein.py
examples/queens/__init__.py
examples/queens/queens.py
examples/rooks/__init__.py
examples/rooks/rooks.py
examples/studentdesks/__init__.py
examples/studentdesks/studentdesks.py
examples/sudoku/__init__.py
examples/sudoku/sudoku.py
examples/wordmath/__init__.py
examples/wordmath/seisseisdoze.py
examples/wordmath/sendmoremoney.py
examples/wordmath/twotwofour.py
examples/xsum/__init__.py
examples/xsum/xsum.py
python_constraint-1.3.1.dist-info/DESCRIPTION.rst
python_constraint-1.3.1.dist-info/METADATA
python_constraint-1.3.1.dist-info/RECORD
python_constraint-1.3.1.dist-info/WHEEL
python_constraint-1.3.1.dist-info/metadata.json
python_constraint-1.3.1.dist-info/top_level.txt
