Metadata-Version: 2.0
Name: python-constraint
Version: 1.3.1
Summary: python-constraint is a module implementing support for handling CSPs (Constraint Solving Problems) over finite domain
Home-page: https://github.com/python-constraint/python-constraint
Author: Gustavo Niemeyer
Author-email: gustavo@niemeyer.net
License: UNKNOWN
Keywords: csp constraint solving problems problem solver
Platform: UNKNOWN
Classifier: Development Status :: 3 - Alpha
Classifier: Environment :: Console
Classifier: Intended Audience :: Science/Research
Classifier: Operating System :: OS Independent
Classifier: Programming Language :: Cython
Classifier: Programming Language :: Python
Classifier: Programming Language :: Python :: 2.6
Classifier: Programming Language :: Python :: 2.7
Classifier: Programming Language :: Python :: 3.3
Classifier: Programming Language :: Python :: 3.4
Classifier: Programming Language :: Python :: 3.4
Classifier: Topic :: Scientific/Engineering
Classifier: License :: OSI Approved :: BSD License
Provides-Extra: dev
Requires-Dist: check-manifest; extra == 'dev'
Requires-Dist: nose; extra == 'dev'
Provides-Extra: test
Requires-Dist: coverage; extra == 'test'
Requires-Dist: nose; extra == 'test'
